pydantic_config_parser/__about__.py
pydantic_config_parser/__init__.py
pydantic_config_parser/json.py
pydantic_config_parser/parser.py
pydantic_config_parser/pydantic.py
pydantic_config_parser/type.py
pydantic_config_parser/yaml.py
pydantic_config_parser-0.1.0.dist-info/METADATA
pydantic_config_parser-0.1.0.dist-info/WHEEL
pydantic_config_parser-0.1.0.dist-info/licenses/LICENSE
pydantic_config_parser-0.1.0.dist-info/RECORD
