Metadata-Version: 2.3
Name: pydantic-config-parser
Version: 0.1.0
Summary: Add your description here
Author-email: pollenjp <polleninjp@gmail.com>
Requires-Python: >=3.12
Requires-Dist: pydantic>=2.10.1
Provides-Extra: yaml
Requires-Dist: pyyaml>=6.0.1; extra == 'yaml'
